cindervm/__init__.py
cindervm/stub.py
cindervm-0.0.3.dist-info/LICENSE
cindervm-0.0.3.dist-info/METADATA
cindervm-0.0.3.dist-info/WHEEL
cindervm-0.0.3.dist-info/top_level.txt
cindervm-0.0.3.dist-info/RECORD
