Metadata-Version: 2.1
Name: cindervm
Version: 0.0.3
Summary: High-performance Python runtime extensions
Home-page: https://github.com/facebookincubator/cinder
Author: Meta Platforms
Author-email: cinder@fb.com
License: UNKNOWN
Platform: UNKNOWN
Classifier: Development Status :: 1 - Planning
Classifier: Programming Language :: Python :: 3.8
Classifier: License :: OSI Approved :: MIT License
Classifier: Operating System :: OS Independent
Requires-Python: ==3.8.*
License-File: LICENSE
